{
	"backtraceGraph" : 
	{
		"commands" : 
		[
			"_install",
			"install",
			"generate_dynamic_reconfigure_options",
			"dynreconf_called",
			"_catkin_package",
			"catkin_package"
		],
		"files" : 
		[
			"/opt/ros/noetic/share/catkin/cmake/custom_install.cmake",
			"/opt/ros/noetic/share/dynamic_reconfigure/cmake/dynamic_reconfigure-macros.cmake",
			"third_party_lib/ira_laser_tools/CMakeLists.txt",
			"/opt/ros/noetic/share/catkin/cmake/catkin_package.cmake"
		],
		"nodes" : 
		[
			{
				"file" : 2
			},
			{
				"command" : 2,
				"file" : 2,
				"line" : 18,
				"parent" : 0
			},
			{
				"command" : 1,
				"file" : 1,
				"line" : 79,
				"parent" : 1
			},
			{
				"command" : 0,
				"file" : 0,
				"line" : 13,
				"parent" : 2
			},
			{
				"command" : 1,
				"file" : 1,
				"line" : 79,
				"parent" : 1
			},
			{
				"command" : 0,
				"file" : 0,
				"line" : 13,
				"parent" : 4
			},
			{
				"command" : 3,
				"file" : 1,
				"line" : 89,
				"parent" : 1
			},
			{
				"command" : 1,
				"file" : 1,
				"line" : 108,
				"parent" : 6
			},
			{
				"command" : 0,
				"file" : 0,
				"line" : 13,
				"parent" : 7
			},
			{
				"command" : 1,
				"file" : 1,
				"line" : 129,
				"parent" : 6
			},
			{
				"command" : 0,
				"file" : 0,
				"line" : 13,
				"parent" : 9
			},
			{
				"command" : 1,
				"file" : 1,
				"line" : 130,
				"parent" : 6
			},
			{
				"command" : 0,
				"file" : 0,
				"line" : 13,
				"parent" : 11
			},
			{
				"command" : 5,
				"file" : 2,
				"line" : 62,
				"parent" : 0
			},
			{
				"command" : 4,
				"file" : 3,
				"line" : 102,
				"parent" : 13
			},
			{
				"command" : 1,
				"file" : 3,
				"line" : 450,
				"parent" : 14
			},
			{
				"command" : 0,
				"file" : 0,
				"line" : 13,
				"parent" : 15
			},
			{
				"command" : 1,
				"file" : 3,
				"line" : 521,
				"parent" : 14
			},
			{
				"command" : 0,
				"file" : 0,
				"line" : 13,
				"parent" : 17
			},
			{
				"command" : 1,
				"file" : 3,
				"line" : 529,
				"parent" : 14
			},
			{
				"command" : 0,
				"file" : 0,
				"line" : 13,
				"parent" : 19
			},
			{
				"command" : 1,
				"file" : 2,
				"line" : 124,
				"parent" : 0
			},
			{
				"command" : 0,
				"file" : 0,
				"line" : 13,
				"parent" : 21
			},
			{
				"command" : 1,
				"file" : 2,
				"line" : 138,
				"parent" : 0
			},
			{
				"command" : 0,
				"file" : 0,
				"line" : 13,
				"parent" : 23
			}
		]
	},
	"installers" : 
	[
		{
			"backtrace" : 3,
			"component" : "Unspecified",
			"destination" : "include/ira_laser_tools",
			"paths" : 
			[
				"build/devel/include/ira_laser_tools/laserscan_multi_mergerConfig.h"
			],
			"type" : "file"
		},
		{
			"backtrace" : 5,
			"component" : "Unspecified",
			"destination" : "include/ira_laser_tools",
			"paths" : 
			[
				"build/devel/include/ira_laser_tools/laserscan_virtualizerConfig.h"
			],
			"type" : "file"
		},
		{
			"backtrace" : 8,
			"component" : "Unspecified",
			"destination" : "lib/python3/dist-packages/ira_laser_tools",
			"paths" : 
			[
				"build/devel/lib/python3/dist-packages/ira_laser_tools/__init__.py"
			],
			"type" : "file"
		},
		{
			"backtrace" : 10,
			"component" : "Unspecified",
			"type" : "code"
		},
		{
			"backtrace" : 12,
			"component" : "Unspecified",
			"destination" : "lib/python3/dist-packages/ira_laser_tools",
			"paths" : 
			[
				"build/devel/lib/python3/dist-packages/ira_laser_tools/cfg"
			],
			"type" : "directory"
		},
		{
			"backtrace" : 16,
			"component" : "Unspecified",
			"destination" : "lib/pkgconfig",
			"paths" : 
			[
				"build/third_party_lib/ira_laser_tools/catkin_generated/installspace/ira_laser_tools.pc"
			],
			"type" : "file"
		},
		{
			"backtrace" : 18,
			"component" : "Unspecified",
			"destination" : "share/ira_laser_tools/cmake",
			"paths" : 
			[
				"build/third_party_lib/ira_laser_tools/catkin_generated/installspace/ira_laser_toolsConfig.cmake",
				"build/third_party_lib/ira_laser_tools/catkin_generated/installspace/ira_laser_toolsConfig-version.cmake"
			],
			"type" : "file"
		},
		{
			"backtrace" : 20,
			"component" : "Unspecified",
			"destination" : "share/ira_laser_tools",
			"paths" : 
			[
				"third_party_lib/ira_laser_tools/package.xml"
			],
			"type" : "file"
		},
		{
			"backtrace" : 22,
			"component" : "Unspecified",
			"destination" : "lib/ira_laser_tools",
			"paths" : 
			[
				"devel/lib/ira_laser_tools/laserscan_multi_merger"
			],
			"targetId" : "laserscan_multi_merger::@65fcd4882f83acc91008",
			"targetIndex" : 103,
			"type" : "target"
		},
		{
			"backtrace" : 22,
			"component" : "Unspecified",
			"destination" : "lib/ira_laser_tools",
			"paths" : 
			[
				"devel/lib/ira_laser_tools/laserscan_virtualizer"
			],
			"targetId" : "laserscan_virtualizer::@65fcd4882f83acc91008",
			"targetIndex" : 104,
			"type" : "target"
		},
		{
			"backtrace" : 24,
			"component" : "Unspecified",
			"destination" : "share/ira_laser_tools/launch",
			"paths" : 
			[
				{
					"from" : "third_party_lib/ira_laser_tools/launch",
					"to" : "."
				}
			],
			"type" : "directory"
		}
	],
	"paths" : 
	{
		"build" : "third_party_lib/ira_laser_tools",
		"source" : "third_party_lib/ira_laser_tools"
	}
}
